src/alu.sv
// ==============================================================================
// Módulo ALU (Arithmetic Logic Unit) para el Procesador RISC-V 32i
// Responsable de ejecutar todas las operaciones aritméticas y lógicas.
// Diseño: Monociclo (combinacional puro).
// ==============================================================================

`timescale 1ns / 1ps
`default_nettype none // Buena práctica: previene la inferencia accidental de nets

module ALU(
    // Entradas
    input  logic signed [31:0] A,        // Operando A (generalmente rs1)
    input  logic signed [31:0] B,        // Operando B (generalmente rs2 o inmediato)
    input  logic         [3:0] ALUOp,    // Código de operación de 4 bits que selecciona la función de la ALU

    // Salidas
    output logic signed [31:0] ALURes    // Resultado de la operación
);
    
    // WORKAROUND para Icarus Verilog: 
    // Extraer el 'shamt' (shift amount) de B fuera del bloque always_comb.
    // Icarus tiene problemas con la selección directa de bits de 'input' en always_comb/ff.
    logic [4:0] shamt;
    assign shamt = B[4:0];

    // Bloque combinacional que describe la lógica de la ALU
    always_comb begin
        // Inicialización por defecto para garantizar que la lógica es combinacional
        ALURes = 32'b0;

        // Estructura case para implementar el multiplexor basado en ALUOp
        case (ALUOp)
            // ------------------------------------------------------------------
            // Operaciones Aritméticas (2'b00 en Func3)
            // ------------------------------------------------------------------
            4'b0000 : ALURes = A + B;                                  // ADD (Suma)
            4'b1000 : ALURes = A - B;                                  // SUB (Resta: bit más significativo de Func7 es '1' para SUB)

            // ------------------------------------------------------------------
            // Operaciones de Desplazamiento (Shift)
            // Usamos la señal 'shamt' intermedia aquí.
            // ------------------------------------------------------------------
            4'b0001 : ALURes = A <<  $unsigned(shamt);                 // SLL (Shift Left Logical - Desplazamiento Lógico a la Izquierda)
            4'b0101 : ALURes = A >>  $unsigned(shamt);                 // SRL (Shift Right Logical - Desplazamiento Lógico a la Derecha)
            4'b1101 : ALURes = A >>> $unsigned(shamt);                 // SRA (Shift Right Arithmetic - Desplazamiento Aritmético a la Derecha)
                                                                       // Nota: >>> preserva el bit de signo de A

            // ------------------------------------------------------------------
            // Operaciones Lógicas
            // ------------------------------------------------------------------
            4'b0100 : ALURes = A ^ B;                                  // XOR (O Exclusiva)
            4'b0110 : ALURes = A | B;                                  // OR (O Lógica)
            4'b0111 : ALURes = A & B;                                  // AND (Y Lógica)

            // ------------------------------------------------------------------
            // Operaciones de Comparación (Set Less Than)
            // ------------------------------------------------------------------
            4'b0010 : ALURes = ($signed(A) < $signed(B)) ? 32'd1 : 32'd0; // SLT (Set Less Than - con signo)
            4'b0011 : ALURes = ($unsigned(A) < $unsigned(B)) ? 32'd1 : 32'd0; // SLTU (Set Less Than Unsigned - sin signo)

            // ------------------------------------------------------------------
            // Operaciones Misceláneas
            // ------------------------------------------------------------------
            4'b1001 : ALURes = B;                                      // Bypass / LUI (Señal de B pasa directamente)

            // ------------------------------------------------------------------
            // Default
            // ------------------------------------------------------------------
            default : ALURes = 32'b0;                                  // Valor por defecto para cualquier código no reconocido
        endcase
    end

endmodule // ALU

tb/tb_alu.sv
// ==============================================================================
// Testbench (TB) para el módulo ALU (Arithmetic Logic Unit)
// Este módulo es combinacional, por lo que no requiere reloj.
// NOTA: Testbench simplificado para máxima compatibilidad con Icarus Verilog,
// utilizando constantes hexadecimales para números negativos (complemento a dos)
// para evitar errores de sintaxis como 'sd-5'.
// ==============================================================================

`timescale 1ns / 1ps
`default_nettype none

module tb_alu;

    // --------------------------------------------------------------------------
    // 1. Declaración de Señales de Conexión
    // --------------------------------------------------------------------------
    localparam integer WIDTH = 32;

    logic signed [WIDTH-1:0] A_in;
    logic signed [WIDTH-1:0] B_in;
    logic         [3:0]      ALUOp_in;
    logic signed [WIDTH-1:0] ALURes_out;

    // --------------------------------------------------------------------------
    // 2. Instanciación del Dispositivo Bajo Prueba (DUT)
    // --------------------------------------------------------------------------
    ALU DUT (
        .A      (A_in),
        .B      (B_in),
        .ALUOp  (ALUOp_in),
        .ALURes (ALURes_out)
    );

    // --------------------------------------------------------------------------
    // 3. Volcado de Formas de Onda (para GTKWave)
    // --------------------------------------------------------------------------
    initial begin
        $dumpfile("wave.vcd");
        $dumpvars(0, tb_alu);
        $display("Generando archivo wave.vcd (ALU). Revise con GTKWave.");
    end

    // --------------------------------------------------------------------------
    // 4. Secuencia de Prueba Principal (Solo Estímulos)
    // --------------------------------------------------------------------------
    initial begin
        // Inicialización
        A_in = 32'h0;
        B_in = 32'h0;
        ALUOp_in = 4'b0000;
        #20; // Espera inicial

        // --- Caso 1: Aritmética (ADD, SUB) ---
        // ADD: 10 + 5
        A_in = 32'd10; 
        B_in = 32'd5; 
        ALUOp_in = 4'b0000;
        #10;

        // SUB: 10 - 5
        A_in = 32'd10; 
        B_in = 32'd5; 
        ALUOp_in = 4'b1000;
        #10;

        // ADD con negativos: -5 (0xFFFFFFFB) + 10
        A_in = 32'hFFFF_FFFB; // -5 en complemento a dos
        B_in = 32'd10; 
        ALUOp_in = 4'b0000;
        #10;

        // --- Caso 2: Operaciones Lógicas (AND, XOR) ---
        A_in = 32'hdeadbeef; 
        B_in = 32'h12345678;

        // AND
        ALUOp_in = 4'b0111;
        #10;

        // XOR
        ALUOp_in = 4'b0100;
        #10;

        // --- Caso 3: Desplazamiento (SLL, SRA) ---
        
        // SLL: 10 << 2
        A_in = 32'd10; 
        B_in = 32'd2; 
        ALUOp_in = 4'b0001;
        #10;

        // SRA: Desplazamiento aritmético con signo: -8 (0xFFFFFFF8) >>> 2
        A_in = 32'hFFFF_FFF8; // -8 en complemento a dos
        B_in = 32'd2; 
        ALUOp_in = 4'b1101;
        #10;

        // --- Caso 4: Comparación (SLT, SLTU) ---

        // SLT (Signed): -5 (0xFFFFFFFB) < 5 -> 1
        A_in = 32'hFFFF_FFFB; // -5 en complemento a dos
        B_in = 32'd5; 
        ALUOp_in = 4'b0010;
        #10;

        // SLTU (Unsigned): Unsigned(-5) vs 5
        A_in = 32'hFFFF_FFFB; // -5 en complemento a dos
        B_in = 32'd5; 
        ALUOp_in = 4'b0011;
        #10;

        // Fin de la simulación
        #100;
        $finish;
    end

endmodule // tb_alu

sim/alu/wave.vcd
$date
	Sun Nov 23 14:55:39 2025
$end
$version
	Icarus Verilog
$end
$timescale
	1ps
$end
$scope module tb_alu $end
$var wire 32 ! ALURes_out [31:0] $end
$var parameter 32 " WIDTH $end
$var reg 4 # ALUOp_in [3:0] $end
$var reg 32 $ A_in [31:0] $end
$var reg 32 % B_in [31:0] $end
$scope module DUT $end
$var wire 32 & A [31:0] $end
$var wire 4 ' ALUOp [3:0] $end
$var wire 32 ( B [31:0] $end
$var wire 5 ) shamt [4:0] $end
$var reg 32 * ALURes [31:0] $end
$upscope $end
$upscope $end
$enddefinitions $end
$comment Show the parameter values. $end
$dumpall
b100000 "
$end
#0
$dumpvars
b0 *
b0 )
b0 (
b0 '
b0 &
b0 %
b0 $
b0 #
b0 !
$end
#20000
b101 )
b1111 !
b1111 *
b101 %
b101 (
b1010 $
b1010 &
#30000
b101 !
b101 *
b1000 #
b1000 '
#40000
b1010 )
b101 !
b101 *
b0 #
b0 '
b1010 %
b1010 (
b11111111111111111111111111111011 $
b11111111111111111111111111111011 &
#50000
b11000 )
b10010001001000001011001101000 !
b10010001001000001011001101000 *
b111 #
b111 '
b10010001101000101011001111000 %
b10010001101000101011001111000 (
b11011110101011011011111011101111 $
b11011110101011011011111011101111 &
#60000
b11001100100110011110100010010111 !
b11001100100110011110100010010111 *
b100 #
b100 '
#70000
b10 )
b101000 !
b101000 *
b1 #
b1 '
b10 %
b10 (
b1010 $
b1010 &
#80000
b11111111111111111111111111111110 !
b11111111111111111111111111111110 *
b1101 #
b1101 '
b11111111111111111111111111111000 $
b11111111111111111111111111111000 &
#90000
b101 )
b1 !
b1 *
b10 #
b10 '
b101 %
b101 (
b11111111111111111111111111111011 $
b11111111111111111111111111111011 &
#100000
b0 !
b0 *
b11 #
b11 '
