src/data_memory.sv
// ============================================================
// RISC-V MONOCICLO - DATA MEMORY
// ------------------------------------------------------------
// Memoria de datos con escritura SINCRÓNICA (reloj)
// y lectura COMBINACIONAL (sin reloj).
// ============================================================

module DATA_MEMORY (
  input  logic        clk,        // reloj
  input  logic [31:0] Address,    // dirección de acceso
  input  logic [31:0] DataWr,     // dato a escribir
  input  logic        DMWr,       // enable de escritura
  input  logic [2:0]  DMCtrl,     // modo de acceso
  output logic [31:0] DataRd      // dato leído
);

  // Memoria de 256 palabras (1 KB)
  logic [31:0] memory [0:255];

  // Índice por palabra (Address / 4)
  logic [7:0] word_index;
  assign word_index = Address[31:2];

  // ============================================================
  // Inicialización interna (sin archivos externos)
  // ============================================================
  initial begin
    integer i;
    for (i = 0; i < 256; i = i + 1)
      memory[i] = 32'b0;

    // Si deseas precargar algunos datos:
    // memory[0] = 32'h00000010;
    // memory[1] = 32'hAABBCCDD;
  end

  // ============================================================
  // Escritura sincrónica (con reloj)
  // ============================================================
  always_ff @(posedge clk) begin
    if (DMWr) begin
      case (DMCtrl)
        3'b000, 3'b100: begin // Byte
          memory[word_index][(Address[1:0]*8)+:8] <= DataWr[7:0];
        end
        3'b001, 3'b101: begin // Halfword
          memory[word_index][(Address[1]*16)+:16] <= DataWr[15:0];
        end
        3'b010: begin // Word
          memory[word_index] <= DataWr;
        end
      endcase
    end
  end

  // ============================================================
  // Lectura combinacional
  // ============================================================
  logic [31:0] temp_word;
  assign temp_word = memory[word_index];

  always_comb begin
    case (DMCtrl)
      3'b000: DataRd = {{24{temp_word[(Address[1:0]*8+7)]}}, temp_word[(Address[1:0]*8)+:8]};  // Byte (signed)
      3'b001: DataRd = {{16{temp_word[(Address[1]*16+15)]}}, temp_word[(Address[1]*16)+:16]}; // Halfword (signed)
      3'b010: DataRd = temp_word;                                                              // Word
      3'b100: DataRd = {24'b0, temp_word[(Address[1:0]*8)+:8]};                               // Byte (unsigned)
      3'b101: DataRd = {16'b0, temp_word[(Address[1]*16)+:16]};                               // Halfword (unsigned)
      default: DataRd = 32'b0;
    endcase
  end

endmodule

tb/tb_data_memory.sv
// ===================================================================
//  Testbench para DATA_MEMORY
// -------------------------------------------------------------------
//  Verifica mediante señales en simulación:
//      • Escritura de palabra completa (word)
//      • Escritura de byte en posiciones específicas
//      • Escritura de halfword según Address[1:0]
//      • Lecturas combinacionales en todos los modos:
//            - Byte / ByteU
//            - Halfword / HalfwordU
//            - Word
// ===================================================================

`timescale 1ns/1ps

module tb_DATA_MEMORY;

    // Entradas al DUT
    logic        clk;
    logic [31:0] Address;
    logic [31:0] DataWr;
    logic        DMWr;
    logic [2:0]  DMCtrl;

    // Salida del DUT
    logic [31:0] DataRd;

    // Instancia del módulo bajo prueba
    DATA_MEMORY dut (
        .clk(clk),
        .Address(Address),
        .DataWr(DataWr),
        .DMWr(DMWr),
        .DMCtrl(DMCtrl),
        .DataRd(DataRd)
    );

    // Generación del reloj
    initial begin
        clk = 0;
        forever #5 clk = ~clk;
    end

    // Archivo VCD
    initial begin
        $dumpfile("wave.vcd");
        $dumpvars(0, tb_DATA_MEMORY);
    end

    // Estímulos sin displays
    initial begin
        Address = 0;
        DataWr  = 0;
        DMWr    = 0;
        DMCtrl  = 0;

        // -----------------------------------------------------------
        // Caso 1: Escritura de WORD en Address = 0
        //         Se espera memory[0] = AABBCCDD
        // -----------------------------------------------------------
        Address = 32'h0000_0000;
        DataWr  = 32'hAABBCCDD;
        DMWr    = 1;
        DMCtrl  = 3'b010;   // word
        #10;
        DMWr = 0;

        // Lectura WORD
        DMCtrl = 3'b010;
        #10;

        // -----------------------------------------------------------
        // Caso 2: Escritura de BYTE en offset 1
        //         Escribe EE → memoria queda: AA BB EE DD
        // -----------------------------------------------------------
        Address = 32'h0000_0001;
        DataWr  = 32'h0000_00EE;
        DMWr    = 1;
        DMCtrl  = 3'b000;   // byte
        #10;
        DMWr = 0;

        // Lectura BYTE signed
        DMCtrl = 3'b000;
        #10;

        // Lectura BYTE unsigned
        DMCtrl = 3'b100;
        #10;

        // -----------------------------------------------------------
        // Caso 3: Escritura de HALFWORD en offset 2
        //         Escribe FF55 → memoria queda: FF 55 EE DD
        // -----------------------------------------------------------
        Address = 32'h0000_0002;
        DataWr  = 32'h0000_FF55;
        DMWr    = 1;
        DMCtrl  = 3'b001;   // halfword
        #10;
        DMWr = 0;

        // Lectura HALFWORD signed
        DMCtrl = 3'b001;
        #10;

        // Lectura HALFWORD unsigned
        DMCtrl = 3'b101;
        #10;

        // -----------------------------------------------------------
        // Caso 4: Escritura de BYTE en offset 3
        //         Escribe 12 → memoria queda: 12 55 EE DD
        // -----------------------------------------------------------
        Address = 32'h0000_0003;
        DataWr  = 32'h0000_0012;
        DMWr    = 1;
        DMCtrl  = 3'b000;   // byte
        #10;
        DMWr = 0;

        // Lectura BYTE unsigned (último byte)
        DMCtrl = 3'b100;
        #10;

        $finish;
    end

endmodule

sim/data_memory/wave.vcd
$date
	Sun Nov 23 17:53:45 2025
$end
$version
	Icarus Verilog
$end
$timescale
	1ps
$end
$scope module tb_DATA_MEMORY $end
$var wire 32 ! DataRd [31:0] $end
$var reg 32 " Address [31:0] $end
$var reg 3 # DMCtrl [2:0] $end
$var reg 1 $ DMWr $end
$var reg 32 % DataWr [31:0] $end
$var reg 1 & clk $end
$scope module dut $end
$var wire 32 ' Address [31:0] $end
$var wire 3 ( DMCtrl [2:0] $end
$var wire 1 $ DMWr $end
$var wire 32 ) DataWr [31:0] $end
$var wire 1 & clk $end
$var wire 32 * temp_word [31:0] $end
$var wire 8 + word_index [7:0] $end
$var reg 32 , DataRd [31:0] $end
$scope begin $unm_blk_4 $end
$var integer 32 - i [31:0] $end
$upscope $end
$upscope $end
$upscope $end
$enddefinitions $end
$comment Show the parameter values. $end
$dumpall
$end
#0
$dumpvars
b100000000 -
b0 ,
b0 +
b0 *
b10101010101110111100110011011101 )
b10 (
b0 '
0&
b10101010101110111100110011011101 %
1$
b10 #
b0 "
b0 !
$end
#5000
b10101010101110111100110011011101 !
b10101010101110111100110011011101 ,
b10101010101110111100110011011101 *
1&
#10000
0&
0$
#15000
1&
#20000
b11111111111111111111111111001100 !
b11111111111111111111111111001100 ,
0&
b0 #
b0 (
1$
b11101110 %
b11101110 )
b1 "
b1 '
#25000
b11111111111111111111111111101110 !
b11111111111111111111111111101110 ,
b10101010101110111110111011011101 *
1&
#30000
0&
0$
#35000
1&
#40000
b11101110 !
b11101110 ,
0&
b100 #
b100 (
#45000
1&
#50000
b11111111111111111010101010111011 !
b11111111111111111010101010111011 ,
0&
b1 #
b1 (
1$
b1111111101010101 %
b1111111101010101 )
b10 "
b10 '
#55000
b11111111111111111111111101010101 !
b11111111111111111111111101010101 ,
b11111111010101011110111011011101 *
1&
#60000
0&
0$
#65000
1&
#70000
b1111111101010101 !
b1111111101010101 ,
0&
b101 #
b101 (
#75000
1&
#80000
b11111111111111111111111111111111 !
b11111111111111111111111111111111 ,
0&
b0 #
b0 (
1$
b10010 %
b10010 )
b11 "
b11 '
#85000
b10010 !
b10010 ,
b10010010101011110111011011101 *
1&
#90000
0&
b100 #
b100 (
0$
