src/branch_unit.sv
// ============================================================
// RISC-V MONOCICLO - BRANCH UNIT
// ------------------------------------------------------------
// Entradas:
//   - rs1, rs2: operandos leídos del banco de registros
//   - BrOp[4:0]: código de operación de salto/branch
//
// Salidas:
//   - NextPCSrc: 1 = usar ALURes como próximo PC (salto tomado)
//                0 = continuar con PC+4
//
// Convención:
//   NextPCSrc BrOp
//   0 00XXX  -> secuencial
//   0 01000  -> BEQ (=)
//   0 01001  -> BNE (≠)
//   0 01100  -> BLT (< signed)
//   0 01101  -> BGE (≥ signed)
//   0 01110  -> BLTU (< unsigned)
//   0 01111  -> BGEU (≥ unsigned)
//   1 1XXXX  -> saltos incondicionales (JAL / JALR)
// ============================================================

module BRANCH_UNIT (
  input  logic [31:0] rs1,
  input  logic [31:0] rs2,
  input  logic [4:0]  BrOp,
  output logic        NextPCSrc
);

  always @(*) begin
    // Valor por defecto: no salto
    NextPCSrc = 1'b0;

    // Saltos incondicionales: BrOp[4] = 1
    if (BrOp[4] == 1'b1) begin
      NextPCSrc = 1'b1;
    end else begin
      // Branches condicionales
      case (BrOp)
        5'b01000: NextPCSrc = (rs1 == rs2);                     // BEQ
        5'b01001: NextPCSrc = (rs1 != rs2);                     // BNE
        5'b01100: NextPCSrc = ($signed(rs1) <  $signed(rs2));   // BLT
        5'b01101: NextPCSrc = ($signed(rs1) >= $signed(rs2));   // BGE
        5'b01110: NextPCSrc = (rs1 <  rs2);                     // BLTU
        5'b01111: NextPCSrc = (rs1 >= rs2);                     // BGEU
        default:  NextPCSrc = 1'b0;                             // No branch
      endcase
    end
  end

endmodule

tb/tb_branch_unit.sv
// ===================================================================
//  Testbench para BRANCH_UNIT
// -------------------------------------------------------------------
//  Verifica mediante señales en simulación:
//      • Evaluación de todas las operaciones de salto condicional
//        (BEQ, BNE, BLT, BGE, BLTU, BGEU)
//      • Activación de salto incondicional (JAL / JALR)
//      • Comportamiento por defecto cuando BrOp no corresponde
// ===================================================================

`timescale 1ns/1ps

module tb_BRANCH_UNIT;

    // Entradas al DUT
    logic [31:0] rs1, rs2;
    logic [4:0]  BrOp;

    // Salida del DUT
    logic NextPCSrc;

    // Instancia del módulo bajo prueba
    BRANCH_UNIT dut (
        .rs1(rs1),
        .rs2(rs2),
        .BrOp(BrOp),
        .NextPCSrc(NextPCSrc)
    );

    // Archivo VCD
    initial begin
        $dumpfile("wave.vcd");
        $dumpvars(0, tb_BRANCH_UNIT);
    end

    // Estímulos sin displays
    initial begin

        // -----------------------------------------------------------
        // Valores base de prueba
        // -----------------------------------------------------------
        rs1 = 32'd5;
        rs2 = 32'd5;

        // -----------------------------------------------------------
        // Caso 1: BEQ (rs1 == rs2)
        // -----------------------------------------------------------
        BrOp = 5'b01000;
        #10;

        // -----------------------------------------------------------
        // Caso 2: BNE (rs1 != rs2)
        // -----------------------------------------------------------
        rs2 = 32'd7;
        BrOp = 5'b01001;
        #10;

        // -----------------------------------------------------------
        // Caso 3: BLT (signed rs1 < rs2)
        // -----------------------------------------------------------
        rs1 = -5;
        rs2 =  3;
        BrOp = 5'b01100;
        #10;

        // -----------------------------------------------------------
        // Caso 4: BGE (signed rs1 >= rs2)
        // -----------------------------------------------------------
        rs1 = 10;
        rs2 = -1;
        BrOp = 5'b01101;
        #10;

        // -----------------------------------------------------------
        // Caso 5: BLTU (unsigned rs1 < rs2)
        // -----------------------------------------------------------
        rs1 = 32'h00000001;
        rs2 = 32'hFFFFFF00;    // muy grande como unsigned
        BrOp = 5'b01110;
        #10;

        // -----------------------------------------------------------
        // Caso 6: BGEU (unsigned rs1 >= rs2)
        // -----------------------------------------------------------
        rs1 = 32'hFFFFFF00;
        rs2 = 32'h00000001;
        BrOp = 5'b01111;
        #10;

        // -----------------------------------------------------------
        // Caso 7: Salto incondicional (JAL/JALR)
        // BrOp[4] = 1
        // -----------------------------------------------------------
        BrOp = 5'b10000;
        #10;

        // -----------------------------------------------------------
        // Caso 8: Valor por defecto (no branch)
        // -----------------------------------------------------------
        BrOp = 5'b00000;
        rs1 = 123;
        rs2 = 456;
        #10;

        $finish;
    end

endmodule

sim/branch_unit/wave.vcd
$date
	Sun Nov 23 17:47:10 2025
$end
$version
	Icarus Verilog
$end
$timescale
	1ps
$end
$scope module tb_BRANCH_UNIT $end
$var wire 1 ! NextPCSrc $end
$var reg 5 " BrOp [4:0] $end
$var reg 32 # rs1 [31:0] $end
$var reg 32 $ rs2 [31:0] $end
$scope module dut $end
$var wire 5 % BrOp [4:0] $end
$var wire 32 & rs1 [31:0] $end
$var wire 32 ' rs2 [31:0] $end
$var reg 1 ! NextPCSrc $end
$upscope $end
$upscope $end
$enddefinitions $end
$comment Show the parameter values. $end
$dumpall
$end
#0
$dumpvars
b101 '
b101 &
b1000 %
b101 $
b101 #
b1000 "
1!
$end
#10000
1!
b1001 "
b1001 %
b111 $
b111 '
#20000
1!
b1100 "
b1100 %
b11 $
b11 '
b11111111111111111111111111111011 #
b11111111111111111111111111111011 &
#30000
1!
b1101 "
b1101 %
b11111111111111111111111111111111 $
b11111111111111111111111111111111 '
b1010 #
b1010 &
#40000
1!
b1110 "
b1110 %
b11111111111111111111111100000000 $
b11111111111111111111111100000000 '
b1 #
b1 &
#50000
1!
b1111 "
b1111 %
b1 $
b1 '
b11111111111111111111111100000000 #
b11111111111111111111111100000000 &
#60000
1!
b10000 "
b10000 %
#70000
0!
b111001000 $
b111001000 '
b1111011 #
b1111011 &
b0 "
b0 %
