src/instruction_memory.sv
// ==============================================================================
// RISC-V MONOCICLO - INSTRUCTION MEMORY
// ------------------------------------------------------------------------------
// Memoria de solo lectura (ROM) de instrucciones.
// Sintetizable en FPGA (usa $readmemh para inicializar).
//
// Entradas:
//    Address      -> dirección del PC (en bytes)
// Salidas:
//    Instruction  -> instrucción leída (32 bits)
//
// Convención:
//    - Cada instrucción ocupa 4 bytes (32 bits).
//    - Address[31:2] se usa como índice porque las
//      instrucciones están alineadas a 4 bytes.
// ==============================================================================

`timescale 1ns / 1ps
`default_nettype none

module INSTRUCTION_MEMORY (
  input  logic [31:0] Address,      // Dirección del PC
  output logic [31:0] Instruction   // Instrucción leída
);

  // Memoria ROM de 256 palabras (1 KB de almacenamiento de instrucciones)
  logic [31:0] memory [0:255];

  // Inicialización: Carga el programa desde el archivo program.hex
  initial begin
    // $readmemh busca el archivo program.hex en el directorio de ejecución
    $readmemh("program.hex", memory);
  end

  // Lectura combinacional: La Instrucción es el contenido de la memoria indexada
  // por Address[31:2] (eliminando los 2 bits menos significativos, ya que
  // las direcciones están alineadas a 4 bytes).
  assign Instruction = memory[Address[31:2]];

endmodule // instruction_memory

tb/tb_instruction_memory.sv
// ==============================================================================
// Testbench (TB) para el módulo INSTRUCTION_MEMORY
// ------------------------------------------------------------------------------
// Módulo combinacional, no requiere reloj. Verifica la lectura correcta
// en direcciones alineadas (0, 4, 8, 0x28, 0x74) y prueba el manejo de 
// direcciones no alineadas.
// **Diseñado solo para generar formas de onda (VCD).**
// ==============================================================================

`timescale 1ns / 1ps
`default_nettype none

module tb_instruction_memory;

    // --------------------------------------------------------------------------
    // 1. Declaración de Señales de Conexión y Parámetros
    // --------------------------------------------------------------------------
    localparam ADDRESS_DELAY = 30; // 30 ns de espera entre cambios de dirección para claridad

    logic [31:0] Address_in;
    logic [31:0] Instruction_out;

    // --------------------------------------------------------------------------
    // 2. Instanciación del Dispositivo Bajo Prueba (DUT)
    // --------------------------------------------------------------------------
    INSTRUCTION_MEMORY DUT (
        .Address     (Address_in),
        .Instruction (Instruction_out)
    );

    // --------------------------------------------------------------------------
    // 3. Volcado de Formas de Onda (para GTKWave)
    // --------------------------------------------------------------------------
    initial begin
        $dumpfile("wave.vcd");
        $dumpvars(0, tb_instruction_memory);
    end

    // --------------------------------------------------------------------------
    // 4. Secuencia de Prueba Principal (Estímulos claros)
    // --------------------------------------------------------------------------
    initial begin
        // 1. Acceso a la primera instrucción (Dirección 0x00, Índice 0)
        // Valor esperado: 40000113
        Address_in = 32'h00000000;
        #ADDRESS_DELAY; 

        // 2. Acceso a la segunda instrucción (Dirección 0x04, Índice 1)
        // Valor esperado: 00800513
        Address_in = 32'h00000004;
        #ADDRESS_DELAY; 

        // 3. Acceso a la tercera instrucción (Dirección 0x08, Índice 2)
        // Valor esperado: 010000EF
        Address_in = 32'h00000008;
        #ADDRESS_DELAY; 
        
        // 4. Acceso a la instrucción en el medio (Dirección 0x28, Índice 10)
        // Valor esperado: 00100313
        Address_in = 32'h00000028;
        #ADDRESS_DELAY; 

        // 5. Prueba de alineación: Dirección no alineada (0x00000029)
        // Address[31:2] sigue siendo 0x28/4 = 10. Valor esperado: 00100313
        Address_in = 32'h00000029;
        #ADDRESS_DELAY; 

        // 6. Acceso a la última instrucción del programa (Dirección 0x74, Índice 29)
        // Valor esperado: 00028513
        Address_in = 32'h00000074;
        #ADDRESS_DELAY; 

        // 7. Acceso inmediatamente fuera de los límites del programa (Dirección 0x78, Índice 30)
        // Valor esperado: 00008067
        Address_in = 32'h00000078;
        #ADDRESS_DELAY; 

        // 8. Acceso a dirección de memoria muy alta, sin inicializar (Índice 200 -> Dirección 0x320)
        // Valor esperado: 00000000 (o 'x')
        Address_in = 32'h00000320;
        #ADDRESS_DELAY; 

        $finish;
    end
endmodule // tb_instruction_memory

sim/instruction_memory/wave.vcd
$date
	Sun Nov 23 15:48:56 2025
$end
$version
	Icarus Verilog
$end
$timescale
	1ps
$end
$scope module tb_instruction_memory $end
$var wire 32 ! Instruction_out [31:0] $end
$var parameter 32 " ADDRESS_DELAY $end
$var reg 32 # Address_in [31:0] $end
$scope module DUT $end
$var wire 32 $ Address [31:0] $end
$var wire 32 % Instruction [31:0] $end
$upscope $end
$upscope $end
$enddefinitions $end
$comment Show the parameter values. $end
$dumpall
b11110 "
$end
#0
$dumpvars
b1000000000000000000000100010011 %
b0 $
b0 #
b1000000000000000000000100010011 !
$end
#30000
b100000000000010100010011 !
b100000000000010100010011 %
b100 #
b100 $
#60000
b1000000000000000011101111 !
b1000000000000000011101111 %
b1000 #
b1000 $
#90000
b100000000001100010011 !
b100000000001100010011 %
b101000 #
b101000 $
#120000
b101001 #
b101001 $
#150000
b101000010100010011 !
b101000010100010011 %
b1110100 #
b1110100 $
#180000
b1000000001100111 !
b1000000001100111 %
b1111000 #
b1111000 $
#210000
bx !
bx %
b1100100000 #
b1100100000 $
