src/control_unit.sv
// ============================================================
// RISC-V MONOCICLO - UNIDAD DE CONTROL PRINCIPAL
// ------------------------------------------------------------
// Genera las señales de control para el datapath monociclo.
// Las señales siguen EXACTAMENTE los nombres y codificaciones
// definidas por el diseño del usuario (Jaider).
// ------------------------------------------------------------
// NextPCSrc es responsabilidad de la Branch Unit (no se maneja aquí).
// ============================================================

module CONTROL_UNIT (
  input  logic [6:0] opcode,
  input  logic [2:0] funct3,
  input  logic [6:0] funct7,

  // --- Señales de control ---
  output logic        RUWr,           // 1 = escribir registro destino
  output logic [1:0]  RUDataWrSrc,    // 00=ALURes, 01=DataMem, 10=PC+4
  output logic        DMWr,           // 1 = escribir en memoria de datos
  output logic [2:0]  DMCtrl,         // control tamaño/signed (B/H/W)
  output logic        ALUASrc,        // 0=rs1, 1=PC
  output logic        ALUBSrc,        // 0=rs2, 1=ImmExt
  output logic [3:0]  ALUOp,          // operación ALU (códigos definidos)
  output logic [2:0]  ImmSrc,         // tipo de inmediato (I,S,B,U,J)
  output logic [4:0]  BrOp            // operación branch (entrada a Branch Unit)
);

  // ------------------------------------------------------------
  // Asignación de valores por defecto.
  // Todas las señales se inicializan en estado seguro.
  // Cada caso del opcode sobrescribe únicamente lo necesario.
  // ------------------------------------------------------------
  always_comb begin
    RUWr         = 1'b0;
    RUDataWrSrc  = 2'b00;
    DMWr         = 1'b0;
    DMCtrl       = 3'b000;
    ALUASrc      = 1'b0;
    ALUBSrc      = 1'b0;
    ALUOp        = 4'b0000;
    ImmSrc       = 3'b000;
    BrOp         = 5'b00000;

    // ------------------------------------------------------------
    // Decodificación principal basada en el campo opcode.
    // Cada tipo de instrucción configura el datapath de manera
    // específica según el estándar RISC-V.
    // ------------------------------------------------------------
    case (opcode)

      // ----------------------------------------------------------
      // R-TYPE (0110011)
      // Operaciones aritméticas y lógicas entre registros.
      // ----------------------------------------------------------
      7'b0110011: begin
        RUWr        = 1'b1;
        RUDataWrSrc = 2'b00;
        ALUASrc     = 1'b0;
        ALUBSrc     = 1'b0;
        ImmSrc      = 3'b000;
        BrOp        = 5'b00000;

        // Selección de operación ALU según funct3/funct7.
        case (funct3)
          3'b000: ALUOp = (funct7 == 7'b0100000) ? 4'b1000 : 4'b0000; // sub/add
          3'b001: ALUOp = 4'b0001; // sll
          3'b010: ALUOp = 4'b0010; // slt
          3'b011: ALUOp = 4'b0011; // sltu
          3'b100: ALUOp = 4'b0100; // xor
          3'b101: ALUOp = (funct7 == 7'b0100000) ? 4'b1101 : 4'b0101; // sra/srl
          3'b110: ALUOp = 4'b0110; // or
          3'b111: ALUOp = 4'b0111; // and
          default: ALUOp = 4'b0000;
        endcase
      end

      // ----------------------------------------------------------
      // I-TYPE (0010011)
      // Operaciones aritméticas/logicas con inmediato.
      // ----------------------------------------------------------
      7'b0010011: begin
        RUWr        = 1'b1;
        RUDataWrSrc = 2'b00;   // resultado de ALU
        DMWr        = 1'b0;
        ALUASrc     = 1'b0;    // rs1
        ALUBSrc     = 1'b1;    // inmediato extendido
        ImmSrc      = 3'b000;  // tipo I
        BrOp        = 5'b00000;

        // Selección de operación ALU según funct3/funct7.
        case (funct3)
          3'b000: ALUOp = 4'b0000; // ADDI
          3'b010: ALUOp = 4'b0010; // SLTI
          3'b011: ALUOp = 4'b0011; // SLTIU
          3'b100: ALUOp = 4'b0100; // XORI
          3'b110: ALUOp = 4'b0110; // ORI
          3'b111: ALUOp = 4'b0111; // ANDI
          3'b001: ALUOp = 4'b0001; // SLLI
          3'b101: ALUOp = (funct7 == 7'b0100000) ? 4'b1101 : 4'b0101; // SRAI/SRLI
          default: ALUOp = 4'b0000;
        endcase
      end

      // ----------------------------------------------------------
      // LOAD (0000011)
      // Carga desde memoria hacia un registro.
      // ----------------------------------------------------------
      7'b0000011: begin
        RUWr        = 1'b1;
        RUDataWrSrc = 2'b01; // DataMem
        DMWr        = 1'b0;
        ALUASrc     = 1'b0;
        ALUBSrc     = 1'b1; // ImmExt
        ALUOp       = 4'b0000; // A + imm
        ImmSrc      = 3'b000; // tipo I
        BrOp        = 5'b00000;

        // Tamaño y signo de carga.
        case (funct3)
          3'b000: DMCtrl = 3'b000; // LB
          3'b001: DMCtrl = 3'b001; // LH
          3'b010: DMCtrl = 3'b010; // LW
          3'b100: DMCtrl = 3'b100; // LBU
          3'b101: DMCtrl = 3'b101; // LHU
          default: DMCtrl = 3'b010;
        endcase
      end

      // ----------------------------------------------------------
      // STORE (0100011)
      // Almacenamiento en memoria de rs2.
      // ----------------------------------------------------------
      7'b0100011: begin
        RUWr        = 1'b0;
        DMWr        = 1'b1;
        ALUASrc     = 1'b0;
        ALUBSrc     = 1'b1;
        ALUOp       = 4'b0000;
        ImmSrc      = 3'b001; // tipo S
        BrOp        = 5'b00000;

        // Tamaño de almacenamiento.
        case (funct3)
          3'b000: DMCtrl = 3'b000; // SB
          3'b001: DMCtrl = 3'b001; // SH
          3'b010: DMCtrl = 3'b010; // SW
          default: DMCtrl = 3'b010;
        endcase
      end

      // ----------------------------------------------------------
      // BRANCH (1100011)
      // Comparaciones y control de flujo condicional.
      // ----------------------------------------------------------
      7'b1100011: begin
        RUWr        = 1'b0;
        DMWr        = 1'b0;
        ALUASrc     = 1'b1;
        ALUBSrc     = 1'b1;
        ALUOp       = 4'b0000; // A - B
        ImmSrc      = 3'b101; // tipo B

        // Codificación de operación de branch.
        case (funct3)
          3'b000: BrOp = 5'b01000; // beq
          3'b001: BrOp = 5'b01001; // bne
          3'b100: BrOp = 5'b01100; // blt
          3'b101: BrOp = 5'b01101; // bge
          3'b110: BrOp = 5'b01110; // bltu
          3'b111: BrOp = 5'b01111; // bgeu
          default: BrOp = 5'b00000;
        endcase
      end

      // ----------------------------------------------------------
      // JAL (1101111)
      // Salto incondicional con inmediato tipo J.
      // ----------------------------------------------------------
      7'b1101111: begin
        RUWr        = 1'b1;
        RUDataWrSrc = 2'b10; // PC+4
        ALUASrc     = 1'b1;
        ALUBSrc     = 1'b1;
        ImmSrc      = 3'b110; // tipo J
        ALUOp       = 4'b0000;
        DMWr        = 1'b0;
        DMCtrl      = 3'b000;
        BrOp        = 5'b10000;
      end

      // ----------------------------------------------------------
      // JALR (1100111)
      // Salto incondicional con inmediato tipo I.
      // ----------------------------------------------------------
      7'b1100111: begin
        RUWr        = 1'b1;
        RUDataWrSrc = 2'b10;
        ALUASrc     = 1'b0;
        ALUBSrc     = 1'b1;
        ImmSrc      = 3'b000;
        ALUOp       = 4'b0000;
        BrOp        = 5'b10000;
      end

      // ----------------------------------------------------------
      // LUI (0110111)
      // Carga inmediata en la parte alta del registro.
      // ----------------------------------------------------------
      7'b0110111: begin
        RUWr        = 1'b1;
        RUDataWrSrc = 2'b00;
        ALUASrc     = 1'b0;
        ALUBSrc     = 1'b1;
        ImmSrc      = 3'b010; // tipo U
        ALUOp       = 4'b0000; // A + imm
        BrOp        = 5'b00000;
      end

      // ----------------------------------------------------------
      // AUIPC (0010111)
      // PC + inmediato tipo U.
      // ----------------------------------------------------------
      7'b0010111: begin
        RUWr        = 1'b1;
        RUDataWrSrc = 2'b00;
        ALUASrc     = 1'b1; // PC
        ALUBSrc     = 1'b1; // ImmExt
        ImmSrc      = 3'b010; // tipo U
        ALUOp       = 4'b0000;
        BrOp        = 5'b00000;
      end

      // ----------------------------------------------------------
      // DEFAULT (NOP)
      // Mantiene señales por defecto.
      // ----------------------------------------------------------
      default: begin
        // valores por defecto
      end
    endcase
  end
endmodule

tb/tb_control_unit.sv
// ===================================================================
//  Testbench para CONTROL_UNIT
// -------------------------------------------------------------------
//  Verifica mediante señales en simulación la correcta generación de:
//      • Señales ALUASrc y ALUBSrc según tipo de instrucción
//      • Selección de ImmSrc para cada formato (I,S,B,U,J)
//      • Señales de escritura RUWr y DMWr
//      • Señales de tamaño DMCtrl para LOAD/STORE
//      • Operaciones ALUOp según funct3/funct7
//      • Codificación de BrOp para instrucciones tipo B
// ===================================================================

`timescale 1ns/1ps

module tb_CONTROL_UNIT;

    // Entradas al DUT
    logic [6:0] opcode;
    logic [2:0] funct3;
    logic [6:0] funct7;

    // Salidas del DUT
    logic        RUWr;
    logic [1:0]  RUDataWrSrc;
    logic        DMWr;
    logic [2:0]  DMCtrl;
    logic        ALUASrc;
    logic        ALUBSrc;
    logic [3:0]  ALUOp;
    logic [2:0]  ImmSrc;
    logic [4:0]  BrOp;

    // Instancia del módulo bajo prueba
    CONTROL_UNIT dut (
        .opcode(opcode),
        .funct3(funct3),
        .funct7(funct7),
        .RUWr(RUWr),
        .RUDataWrSrc(RUDataWrSrc),
        .DMWr(DMWr),
        .DMCtrl(DMCtrl),
        .ALUASrc(ALUASrc),
        .ALUBSrc(ALUBSrc),
        .ALUOp(ALUOp),
        .ImmSrc(ImmSrc),
        .BrOp(BrOp)
    );

    // Archivo VCD
    initial begin
        $dumpfile("wave.vcd");
        $dumpvars(0, tb_CONTROL_UNIT);
    end

    // Estímulos sin displays
    initial begin

        // -----------------------------------------------------------
        // Caso 1: R-TYPE (ADD)
        // -----------------------------------------------------------
        opcode = 7'b0110011;
        funct3 = 3'b000;
        funct7 = 7'b0000000;
        #10;

        // -----------------------------------------------------------
        // Caso 2: I-TYPE (ADDI)
        // -----------------------------------------------------------
        opcode = 7'b0010011;
        funct3 = 3'b000;
        funct7 = 7'b0000000;
        #10;

        // -----------------------------------------------------------
        // Caso 3: LOAD (LW)
        // -----------------------------------------------------------
        opcode = 7'b0000011;
        funct3 = 3'b010;
        funct7 = 7'b0000000;
        #10;

        // -----------------------------------------------------------
        // Caso 4: STORE (SW)
        // -----------------------------------------------------------
        opcode = 7'b0100011;
        funct3 = 3'b010;
        funct7 = 7'b0000000;
        #10;

        // -----------------------------------------------------------
        // Caso 5: BRANCH (BEQ)
        // -----------------------------------------------------------
        opcode = 7'b1100011;
        funct3 = 3'b000;
        funct7 = 7'b0000000;
        #10;

        // -----------------------------------------------------------
        // Caso 6: JAL
        // -----------------------------------------------------------
        opcode = 7'b1101111;
        funct3 = 3'b000;
        funct7 = 7'b0000000;
        #10;

        // -----------------------------------------------------------
        // Caso 7: JALR
        // -----------------------------------------------------------
        opcode = 7'b1100111;
        funct3 = 3'b000;
        funct7 = 7'b0000000;
        #10;

        // -----------------------------------------------------------
        // Caso 8: LUI
        // -----------------------------------------------------------
        opcode = 7'b0110111;
        funct3 = 3'b000;
        funct7 = 7'b0000000;
        #10;

        // -----------------------------------------------------------
        // Caso 9: AUIPC
        // -----------------------------------------------------------
        opcode = 7'b0010111;
        funct3 = 3'b000;
        funct7 = 7'b0000000;
        #10;

        $finish;
    end

endmodule

sim/control_unit/wave.vcd
$date
	Sun Nov 23 17:40:00 2025
$end
$version
	Icarus Verilog
$end
$timescale
	1ps
$end
$scope module tb_CONTROL_UNIT $end
$var wire 1 ! RUWr $end
$var wire 2 " RUDataWrSrc [1:0] $end
$var wire 3 # ImmSrc [2:0] $end
$var wire 1 $ DMWr $end
$var wire 3 % DMCtrl [2:0] $end
$var wire 5 & BrOp [4:0] $end
$var wire 4 ' ALUOp [3:0] $end
$var wire 1 ( ALUBSrc $end
$var wire 1 ) ALUASrc $end
$var reg 3 * funct3 [2:0] $end
$var reg 7 + funct7 [6:0] $end
$var reg 7 , opcode [6:0] $end
$scope module dut $end
$var wire 3 - funct3 [2:0] $end
$var wire 7 . funct7 [6:0] $end
$var wire 7 / opcode [6:0] $end
$var reg 1 ) ALUASrc $end
$var reg 1 ( ALUBSrc $end
$var reg 4 0 ALUOp [3:0] $end
$var reg 5 1 BrOp [4:0] $end
$var reg 3 2 DMCtrl [2:0] $end
$var reg 1 $ DMWr $end
$var reg 3 3 ImmSrc [2:0] $end
$var reg 2 4 RUDataWrSrc [1:0] $end
$var reg 1 ! RUWr $end
$upscope $end
$upscope $end
$enddefinitions $end
$comment Show the parameter values. $end
$dumpall
$end
#0
$dumpvars
b0 4
b0 3
b0 2
b0 1
b0 0
b110011 /
b0 .
b0 -
b110011 ,
b0 +
b0 *
0)
0(
b0 '
b0 &
b0 %
0$
b0 #
b0 "
1!
$end
#10000
1(
1!
b10011 ,
b10011 /
#20000
b10 %
b10 2
b1 "
b1 4
1(
1!
b10 *
b10 -
b11 ,
b11 /
#30000
b1 #
b1 3
1$
1(
b10 %
b10 2
b0 "
b0 4
0!
b100011 ,
b100011 /
#40000
b1000 &
b1000 1
1)
b101 #
b101 3
1(
b0 %
b0 2
0$
b0 *
b0 -
b1100011 ,
b1100011 /
#50000
b10 "
b10 4
1!
b10000 &
b10000 1
b110 #
b110 3
1(
1)
b1101111 ,
b1101111 /
#60000
b10000 &
b10000 1
b0 #
b0 3
1(
0)
b10 "
b10 4
1!
b1100111 ,
b1100111 /
#70000
b10 #
b10 3
b0 &
b0 1
1(
b0 "
b0 4
1!
b110111 ,
b110111 /
#80000
1)
b10 #
b10 3
1(
1!
b10111 ,
b10111 /
